ezWxPython/__init__.py
ezWxPython/ezWxPython.py
ezWxPython/demo/AllControls.py
ezWxPython/demo/AnalogClock.py
ezWxPython/demo/CalendarCtrl.py
ezWxPython/demo/ContextMenu.py
ezWxPython/demo/ControlDemo.py
ezWxPython/demo/CustomDialog.py
ezWxPython/demo/DirectoryDialog.py
ezWxPython/demo/DragFrame.py
ezWxPython/demo/Execute.py
ezWxPython/demo/FileBrowser.py
ezWxPython/demo/FileDialog.py
ezWxPython/demo/Gauge.py
ezWxPython/demo/IdleEvent.py
ezWxPython/demo/Layout.py
ezWxPython/demo/LedNumber.py
ezWxPython/demo/MenuBar.py
ezWxPython/demo/MultiSplitWindow.py
ezWxPython/demo/NoFrame.py
ezWxPython/demo/Notebook.py
ezWxPython/demo/PopupWindow.py
ezWxPython/demo/ProgressDialog.py
ezWxPython/demo/ProgressIndicator.py
ezWxPython/demo/SimpleFrame.py
ezWxPython/demo/Simplebook.py
ezWxPython/demo/SplitWindow.py
ezWxPython/demo/StatusBar.py
ezWxPython/demo/TextEntryDialog.py
ezWxPython/demo/Thread.py
ezWxPython/demo/Ticker.py
ezWxPython/demo/TimerEvent.py
ezWxPython/demo/ToolbarText.py
ezWxPython/example/FtpServer.py
ezWxPython/example/IconMaker.py
ezWxPython/example/VideoPlayer.py
ezWxPython-0.4.7.dist-info/METADATA
ezWxPython-0.4.7.dist-info/WHEEL
ezWxPython-0.4.7.dist-info/top_level.txt
ezWxPython-0.4.7.dist-info/RECORD
