Metadata-Version: 2.1
Name: ezWxPython
Version: 0.4.7
Summary: Easy wxPython wrapper
Home-page: https://github.com/zdivdev/ezWxPython
Author: zdiv
Author-email: zdiv@daum.net
License: UNKNOWN
Keywords: GUI UI wxpython wrapper simple easy beginner novice student graphics
Platform: UNKNOWN
Classifier: Programming Language :: Python :: 3
Classifier: Programming Language :: Python :: 3.6
Classifier: Programming Language :: Python :: 3.7
Classifier: License :: OSI Approved :: MIT License
Classifier: Operating System :: OS Independent
